[{"name": "benchmarks.AssignSingleDfToNestedSeries.peakmem_run", "idx": null, "pretty_name": "benchmarks.AssignSingleDfToNestedSeries.peakmem_run", "last_rev": 470, "last_value": 274223104.0, "last_err": 229691.07692307694, "prev_value": 269457408.0, "change_rev": [411, 420]}, {"name": "benchmarks.AssignSingleDfToNestedSeries.time_run", "idx": null, "pretty_name": "benchmarks.AssignSingleDfToNestedSeries.time_run", "last_rev": 470, "last_value": 0.023165428000027077, "last_err": 0.0012201935328666363, "prev_value": null, "change_rev": null}, {"name": "benchmarks.NestedFrameAddNested.peakmem_run", "idx": null, "pretty_name": "benchmarks.NestedFrameAddNested.peakmem_run", "last_rev": 470, "last_value": 91617280.0, "last_err": 1381627.8032786886, "prev_value": null, "change_rev": null}, {"name": "benchmarks.NestedFrameAddNested.time_run", "idx": null, "pretty_name": "benchmarks.NestedFrameAddNested.time_run", "last_rev": 470, "last_value": 0.008736686999995413, "last_err": 0.0006107722218304963, "prev_value": null, "change_rev": null}, {"name": "benchmarks.NestedFrameQuery.peakmem_run", "idx": null, "pretty_name": "benchmarks.NestedFrameQuery.peakmem_run", "last_rev": 470, "last_value": 95623168.0, "last_err": 1248205.6393442622, "prev_value": null, "change_rev": null}, {"name": "benchmarks.NestedFrameQuery.time_run", "idx": null, "pretty_name": "benchmarks.NestedFrameQuery.time_run", "last_rev": 470, "last_value": 0.0063143835000119, "last_err": 0.002106068030673264, "prev_value": null, "change_rev": null}, {"name": "benchmarks.NestedFrameReduce.peakmem_run", "idx": null, "pretty_name": "benchmarks.NestedFrameReduce.peakmem_run", "last_rev": 470, "last_value": 94855168.0, "last_err": 1222857.4426229508, "prev_value": null, "change_rev": null}, {"name": "benchmarks.NestedFrameReduce.time_run", "idx": null, "pretty_name": "benchmarks.NestedFrameReduce.time_run", "last_rev": 470, "last_value": 0.0012599104999995664, "last_err": 2.1449077684772407e-05, "prev_value": 0.0010203743636338913, "change_rev": [225, 228]}, {"name": "benchmarks.ReassignHalfOfNestedSeries.peakmem_run", "idx": null, "pretty_name": "benchmarks.ReassignHalfOfNestedSeries.peakmem_run", "last_rev": 470, "last_value": 293281792.0, "last_err": 237568.0, "prev_value": 288585728.0, "change_rev": [411, 420]}, {"name": "benchmarks.ReassignHalfOfNestedSeries.time_run", "idx": null, "pretty_name": "benchmarks.ReassignHalfOfNestedSeries.time_run", "last_rev": 470, "last_value": 0.04539132150000569, "last_err": 0.005070841805654501, "prev_value": 0.030499254999995173, "change_rev": [310, 314]}]