[{"name": "benchmarks.AssignSingleDfToNestedSeries.peakmem_run", "idx": null, "pretty_name": "benchmarks.AssignSingleDfToNestedSeries.peakmem_run", "last_rev": 828, "last_value": 268234752.0, "last_err": 8371577.263157895, "prev_value": null, "change_rev": null}, {"name": "benchmarks.AssignSingleDfToNestedSeries.time_run", "idx": null, "pretty_name": "benchmarks.AssignSingleDfToNestedSeries.time_run", "last_rev": 828, "last_value": 0.02329289049998806, "last_err": 0.0032682275840817962, "prev_value": null, "change_rev": null}, {"name": "benchmarks.CountNestedBy.peakmem_run", "idx": null, "pretty_name": "benchmarks.CountNestedBy.peakmem_run", "last_rev": 828, "last_value": 133607424.0, "last_err": 4006916.145748988, "prev_value": null, "change_rev": null}, {"name": "benchmarks.CountNestedBy.time_run", "idx": null, "pretty_name": "benchmarks.CountNestedBy.time_run", "last_rev": 828, "last_value": 0.06545598699999289, "last_err": 0.007247507665364224, "prev_value": 0.4669797610000046, "change_rev": [null, 517]}, {"name": "benchmarks.NestedFrameAddNested.peakmem_run", "idx": null, "pretty_name": "benchmarks.NestedFrameAddNested.peakmem_run", "last_rev": 828, "last_value": 99688448.0, "last_err": 5268865.55465587, "prev_value": null, "change_rev": null}, {"name": "benchmarks.NestedFrameAddNested.time_run", "idx": null, "pretty_name": "benchmarks.NestedFrameAddNested.time_run", "last_rev": 828, "last_value": 0.009516884749999122, "last_err": 0.0014224279560380434, "prev_value": null, "change_rev": null}, {"name": "benchmarks.NestedFrameQuery.peakmem_run", "idx": null, "pretty_name": "benchmarks.NestedFrameQuery.peakmem_run", "last_rev": 828, "last_value": 103477248.0, "last_err": 5606561.684210527, "prev_value": null, "change_rev": null}, {"name": "benchmarks.NestedFrameQuery.time_run", "idx": null, "pretty_name": "benchmarks.NestedFrameQuery.time_run", "last_rev": 828, "last_value": 0.01091810724999931, "last_err": 0.00034502176169927683, "prev_value": 0.006950681000006398, "change_rev": [null, 270]}, {"name": "benchmarks.NestedFrameReduce.peakmem_run", "idx": null, "pretty_name": "benchmarks.NestedFrameReduce.peakmem_run", "last_rev": 828, "last_value": 103391232.0, "last_err": 5435806.574898785, "prev_value": null, "change_rev": null}, {"name": "benchmarks.NestedFrameReduce.time_run", "idx": null, "pretty_name": "benchmarks.NestedFrameReduce.time_run", "last_rev": 828, "last_value": 0.0010537309499994763, "last_err": 9.637824332576725e-05, "prev_value": 0.0012370157777783991, "change_rev": [null, 815]}, {"name": "benchmarks.ReadFewColumnsHTTPS.peakmem_run", "idx": null, "pretty_name": "benchmarks.ReadFewColumnsHTTPS.peakmem_run", "last_rev": 828, "last_value": 191811584.0, "last_err": 1539185.7777777778, "prev_value": 178161664.0, "change_rev": [812, 814]}, {"name": "benchmarks.ReadFewColumnsHTTPS.time_run", "idx": null, "pretty_name": "benchmarks.ReadFewColumnsHTTPS.time_run", "last_rev": 828, "last_value": 0.3652279355000019, "last_err": 0.2405465117441692, "prev_value": 2.7411992384999877, "change_rev": [null, 691]}, {"name": "benchmarks.ReadFewColumnsS3.peakmem_run", "idx": null, "pretty_name": "benchmarks.ReadFewColumnsS3.peakmem_run", "last_rev": 828, "last_value": 1229758464.0, "last_err": 29860901.925925925, "prev_value": 1338245120.0, "change_rev": [775, 778]}, {"name": "benchmarks.ReadFewColumnsS3.time_run", "idx": null, "pretty_name": "benchmarks.ReadFewColumnsS3.time_run", "last_rev": 828, "last_value": 0.7029555989999992, "last_err": 0.5208188763329474, "prev_value": 1.8187031429999934, "change_rev": [775, 778]}, {"name": "benchmarks.ReassignHalfOfNestedSeries.peakmem_run", "idx": null, "pretty_name": "benchmarks.ReassignHalfOfNestedSeries.peakmem_run", "last_rev": 828, "last_value": 287539200.0, "last_err": 10969552.32388664, "prev_value": null, "change_rev": null}, {"name": "benchmarks.ReassignHalfOfNestedSeries.time_run", "idx": null, "pretty_name": "benchmarks.ReassignHalfOfNestedSeries.time_run", "last_rev": 828, "last_value": 0.04898819749999461, "last_err": 0.002597883337070946, "prev_value": 0.044106365999937225, "change_rev": [null, 688]}]