[{"name": "benchmarks.AssignSingleDfToNestedSeries.peakmem_run", "idx": null, "pretty_name": "benchmarks.AssignSingleDfToNestedSeries.peakmem_run", "last_rev": 156, "last_value": 256649216.0, "last_err": 1652297.142857143, "prev_value": 215633920.0, "change_rev": [69, 78]}, {"name": "benchmarks.AssignSingleDfToNestedSeries.time_run", "idx": null, "pretty_name": "benchmarks.AssignSingleDfToNestedSeries.time_run", "last_rev": 156, "last_value": 0.03311112250000292, "last_err": 0.0013415115778842878, "prev_value": 0.006260144666669021, "change_rev": [69, 78]}, {"name": "benchmarks.NestedFrameAddNested.peakmem_run", "idx": null, "pretty_name": "benchmarks.NestedFrameAddNested.peakmem_run", "last_rev": 156, "last_value": 85970944.0, "last_err": 198340.92307692306, "prev_value": null, "change_rev": null}, {"name": "benchmarks.NestedFrameAddNested.time_run", "idx": null, "pretty_name": "benchmarks.NestedFrameAddNested.time_run", "last_rev": 156, "last_value": 0.008643371500006936, "last_err": 0.00034165447893291735, "prev_value": null, "change_rev": null}, {"name": "benchmarks.NestedFrameQuery.peakmem_run", "idx": null, "pretty_name": "benchmarks.NestedFrameQuery.peakmem_run", "last_rev": 156, "last_value": 89542656.0, "last_err": 257228.8, "prev_value": 88238080.0, "change_rev": [127, 129]}, {"name": "benchmarks.NestedFrameQuery.time_run", "idx": null, "pretty_name": "benchmarks.NestedFrameQuery.time_run", "last_rev": 156, "last_value": 0.006308662249999486, "last_err": 0.00022118890353565264, "prev_value": 0.008386717999997018, "change_rev": [107, 112]}, {"name": "benchmarks.NestedFrameReduce.peakmem_run", "idx": null, "pretty_name": "benchmarks.NestedFrameReduce.peakmem_run", "last_rev": 156, "last_value": 89542656.0, "last_err": 133120.0, "prev_value": 88238080.0, "change_rev": [127, 129]}, {"name": "benchmarks.NestedFrameReduce.time_run", "idx": null, "pretty_name": "benchmarks.NestedFrameReduce.time_run", "last_rev": 156, "last_value": 0.0051824558333256245, "last_err": 0.00013503620018394153, "prev_value": null, "change_rev": null}, {"name": "benchmarks.ReassignHalfOfNestedSeries.peakmem_run", "idx": null, "pretty_name": "benchmarks.ReassignHalfOfNestedSeries.peakmem_run", "last_rev": 156, "last_value": 274980864.0, "last_err": 3123200.0, "prev_value": 337629184.0, "change_rev": [69, 78]}, {"name": "benchmarks.ReassignHalfOfNestedSeries.time_run", "idx": null, "pretty_name": "benchmarks.ReassignHalfOfNestedSeries.time_run", "last_rev": 156, "last_value": 0.060105348500016476, "last_err": 0.004851922458626673, "prev_value": 2.4009557010000435, "change_rev": [69, 78]}]