[{"name": "benchmarks.AssignSingleDfToNestedSeries.peakmem_run", "idx": null, "pretty_name": "benchmarks.AssignSingleDfToNestedSeries.peakmem_run", "last_rev": 222, "last_value": 257396736.0, "last_err": 2051137.3617021276, "prev_value": 215633920.0, "change_rev": [69, 78]}, {"name": "benchmarks.AssignSingleDfToNestedSeries.time_run", "idx": null, "pretty_name": "benchmarks.AssignSingleDfToNestedSeries.time_run", "last_rev": 222, "last_value": 0.03253270349999582, "last_err": 0.0013517421626559067, "prev_value": 0.006260144666669021, "change_rev": [69, 78]}, {"name": "benchmarks.NestedFrameAddNested.peakmem_run", "idx": null, "pretty_name": "benchmarks.NestedFrameAddNested.peakmem_run", "last_rev": 222, "last_value": 85970944.0, "last_err": 714342.4, "prev_value": null, "change_rev": null}, {"name": "benchmarks.NestedFrameAddNested.time_run", "idx": null, "pretty_name": "benchmarks.NestedFrameAddNested.time_run", "last_rev": 222, "last_value": 0.008819341249999724, "last_err": 0.00037634494353181315, "prev_value": null, "change_rev": null}, {"name": "benchmarks.NestedFrameQuery.peakmem_run", "idx": null, "pretty_name": "benchmarks.NestedFrameQuery.peakmem_run", "last_rev": 222, "last_value": 89268224.0, "last_err": 1301435.7333333334, "prev_value": null, "change_rev": null}, {"name": "benchmarks.NestedFrameQuery.time_run", "idx": null, "pretty_name": "benchmarks.NestedFrameQuery.time_run", "last_rev": 222, "last_value": 0.0062953004999926065, "last_err": 0.00021605554261758811, "prev_value": 0.008386717999997018, "change_rev": [107, 112]}, {"name": "benchmarks.NestedFrameReduce.peakmem_run", "idx": null, "pretty_name": "benchmarks.NestedFrameReduce.peakmem_run", "last_rev": 222, "last_value": 88358912.0, "last_err": 999332.9777777778, "prev_value": null, "change_rev": null}, {"name": "benchmarks.NestedFrameReduce.time_run", "idx": null, "pretty_name": "benchmarks.NestedFrameReduce.time_run", "last_rev": 222, "last_value": 0.001082872100002419, "last_err": 8.707133192098325e-05, "prev_value": 0.00518108125000083, "change_rev": [162, 165]}, {"name": "benchmarks.ReassignHalfOfNestedSeries.peakmem_run", "idx": null, "pretty_name": "benchmarks.ReassignHalfOfNestedSeries.peakmem_run", "last_rev": 222, "last_value": 276099072.0, "last_err": 3624437.1063829786, "prev_value": 337629184.0, "change_rev": [69, 78]}, {"name": "benchmarks.ReassignHalfOfNestedSeries.time_run", "idx": null, "pretty_name": "benchmarks.ReassignHalfOfNestedSeries.time_run", "last_rev": 222, "last_value": 0.05868106750000379, "last_err": 0.0038371701170488415, "prev_value": 2.4009557010000435, "change_rev": [69, 78]}]